braque.py
braque-1.0.7.dist-info/METADATA
braque-1.0.7.dist-info/WHEEL
braque-1.0.7.dist-info/licenses/LICENSE
braque-1.0.7.dist-info/RECORD
