Metadata-Version: 2.1
Name: braque
Version: 1.0.7
Summary: BRAQUE is a pipeline for clustering high dimensional data, specifically it was built for and tested on proteomics data acquired through immunofluorescence technique.
Project-URL: Homepage, https://github.com/LorenzoDallOlio/BRAQUE
Project-URL: Bug Tracker, https://github.com/LorenzoDallOlio/BRAQUE/issues
Author-email: Lorenzo Dall'Olio <lorenzo.dallolio4@unibo.it>
License-File: LICENSE
Classifier: Development Status :: 4 - Beta
Classifier: License :: OSI Approved :: GNU General Public License v3 (GPLv3)
Classifier: Operating System :: OS Independent
Classifier: Programming Language :: Python :: 3
Requires-Python: >=3.7
Requires-Dist: contourpy>=1.1.0
Requires-Dist: cycler>=0.11.0
Requires-Dist: cython>=0.29.35
Requires-Dist: fonttools>=4.40.0
Requires-Dist: hdbscan>=0.8.29
Requires-Dist: joblib>=1.2.0
Requires-Dist: kiwisolver>=1.4.4
Requires-Dist: llvmlite>=0.40.1rc1
Requires-Dist: matplotlib>=3.7.1
Requires-Dist: numba>=0.57.0
Requires-Dist: numpy>=1.24.3
Requires-Dist: packaging>=23.1
Requires-Dist: pandas>=2.0.2
Requires-Dist: pillow>=9.5.0
Requires-Dist: pynndescent>=0.5.10
Requires-Dist: pyparsing>=3.1.0
Requires-Dist: python-dateutil>=2.8.2
Requires-Dist: pytz>=2023.3
Requires-Dist: scikit-learn>=1.2.2
Requires-Dist: scipy>=1.10.1
Requires-Dist: seaborn>=0.12.2
Requires-Dist: six>=1.16.0
Requires-Dist: threadpoolctl>=3.1.0
Requires-Dist: tqdm>=4.65.0
Requires-Dist: tzdata>=2023.3
Requires-Dist: umap-learn>=0.5.3
